README.md
setup.py
ediri_stackit/__init__.py
ediri_stackit/_inputs.py
ediri_stackit/_utilities.py
ediri_stackit/affinity_group.py
ediri_stackit/authorization_organization_role_assignment.py
ediri_stackit/authorization_project_role_assignment.py
ediri_stackit/cdn_custom_domain.py
ediri_stackit/cdn_distribution.py
ediri_stackit/dns_record_set.py
ediri_stackit/dns_zone.py
ediri_stackit/get_affinity_group.py
ediri_stackit/get_cdn_custom_domain.py
ediri_stackit/get_cdn_distribution.py
ediri_stackit/get_dns_record_set.py
ediri_stackit/get_dns_zone.py
ediri_stackit/get_git.py
ediri_stackit/get_iaas_project.py
ediri_stackit/get_image.py
ediri_stackit/get_key_pair.py
ediri_stackit/get_loadbalancer.py
ediri_stackit/get_logme_credential.py
ediri_stackit/get_logme_instance.py
ediri_stackit/get_mariadb_credential.py
ediri_stackit/get_mariadb_instance.py
ediri_stackit/get_mongodbflex_instance.py
ediri_stackit/get_mongodbflex_user.py
ediri_stackit/get_network.py
ediri_stackit/get_network_area.py
ediri_stackit/get_network_area_route.py
ediri_stackit/get_network_interface.py
ediri_stackit/get_objectstorage_bucket.py
ediri_stackit/get_objectstorage_credential.py
ediri_stackit/get_objectstorage_credentials_group.py
ediri_stackit/get_observability_alertgroup.py
ediri_stackit/get_observability_instance.py
ediri_stackit/get_observability_logalertgroup.py
ediri_stackit/get_observability_scrapeconfig.py
ediri_stackit/get_opensearch_credential.py
ediri_stackit/get_opensearch_instance.py
ediri_stackit/get_postgresflex_database.py
ediri_stackit/get_postgresflex_instance.py
ediri_stackit/get_postgresflex_user.py
ediri_stackit/get_public_ip.py
ediri_stackit/get_public_ip_ranges.py
ediri_stackit/get_rabbitmq_credential.py
ediri_stackit/get_rabbitmq_instance.py
ediri_stackit/get_redis_credential.py
ediri_stackit/get_redis_instance.py
ediri_stackit/get_resourcemanager_project.py
ediri_stackit/get_routing_table.py
ediri_stackit/get_routing_table_route.py
ediri_stackit/get_routing_table_routes.py
ediri_stackit.egg-info/PKG-INFO
ediri_stackit.egg-info/SOURCES.txt
ediri_stackit.egg-info/dependency_links.txt
ediri_stackit.egg-info/not-zip-safe
ediri_stackit.egg-info/requires.txt
ediri_stackit.egg-info/top_level.txt
