Metadata-Version: 2.1
Name: ediri-stackit
Version: 0.2.6
Summary: A Pulumi package for creating and managing stackit resources.
Home-page: https://www.pulumi.com
License: Apache-2.0
Project-URL: Repository, https://github.com/dirien/pulumi-stackit
Keywords: pulumi stackit category/utility
Platform: UNKNOWN
Requires-Python: >=3.9
